{                                                      
	                                            
	"rows":[                                                          
{"col1":"全身","col2":" ","col3":" ","col4":" "},         
{"col1":" ","col2":"消瘦","col3":"0","col4":"0"},         
{"col1":" ","col2":"发育不良","col3":"0","col4":"0"},        
{"col1":" ","col2":"下肢水肿","col3":"0","col4":"0"},

{"col1":"皮肤","col2":" ","col3":" ","col4":" "},         
{"col1":" ","col2":"毛囊角化","col3":"0","col4":"0"},         
{"col1":" ","col2":"皮炎（有红斑疹）","col3":"0","col4":"0"},        
{"col1":" ","col2":"脂溢性皮炎","col3":"0","col4":"0"},  
{"col1":" ","col2":"出血点","col3":"0","col4":"0"},  

{"col1":"眼睛","col2":" ","col3":" ","col4":" "},         
{"col1":" ","col2":"角膜干燥","col3":"0","col4":"0"},         
{"col1":" ","col2":"夜盲","col3":"0","col4":"0"},        
{"col1":" ","col2":"角膜边缘充血","col3":"0","col4":"0"},
{"col1":" ","col2":"睑缘炎","col3":"0","col4":"0"},        
{"col1":" ","col2":"羞明（畏光）","col3":"2","col4":"1.3"},

{"col1":"口唇","col2":" ","col3":" ","col4":" "},         
{"col1":" ","col2":"苍白","col3":"0","col4":"0"},         
{"col1":" ","col2":"口唇炎","col3":"0","col4":"0"},        
{"col1":" ","col2":"口角炎","col3":"0","col4":"0"},
{"col1":" ","col2":"口角裂","col3":"0","col4":"0"},

{"col1":"口腔","col2":" ","col3":" ","col4":" "},         
{"col1":" ","col2":"舌炎","col3":"0","col4":"0"},         
{"col1":" ","col2":"舌猩红，舌肉红","col3":"0","col4":"0"},        
{"col1":" ","col2":"地图舌","col3":"0","col4":"0"},
{"col1":" ","col2":"舌水肿（可见牙咬痕）","col3":"0","col4":"0"},        
{"col1":" ","col2":"口内炎","col3":"0","col4":"0"},
{"col1":" ","col2":"牙龈炎","col3":"0","col4":"0"},        
{"col1":" ","col2":"牙龈出血","col3":"0","col4":"0"},

{"col1":"胸和腿","col2":" ","col3":" ","col4":" "},         
{"col1":" ","col2":"鸡胸","col3":"0","col4":"0"},         
{"col1":" ","col2":"肋骨串珠","col3":"0","col4":"0"},        
{"col1":" ","col2":"“O”型腿","col3":"0","col4":"0"},      
{"col1":" ","col2":"“X”型腿","col3":"0","col4":"0"}		
	]                                                          
}                                                           
			
			
			
			
	
			
			
			
			
						
			
			
			
			
			

			
			
			
			
			

